edaviz_analyser/__init__.py
edaviz_analyser/eda.py
edaviz_analyser-0.1.1.1.dist-info/LICENSE
edaviz_analyser-0.1.1.1.dist-info/METADATA
edaviz_analyser-0.1.1.1.dist-info/WHEEL
edaviz_analyser-0.1.1.1.dist-info/top_level.txt
edaviz_analyser-0.1.1.1.dist-info/RECORD
